Lab10/ex2/ex2.v
module ex2
(
	i_bit1,
	i_bit2,
	cin,
	cout,
	sum
);

input i_bit1;
input i_bit2;
input cin;
output sum;
output cout;
assign sum = i_bit1 ^ i_bit2 ^ cin;
assign cout = (i_bit1 & i_bit2) | ((i_bit1 ^ i_bit2) & cin);
endmodule

Lab10/ex2/testbench.v
module testbench;

// input and output test signals
reg a, b, carry_in;

wire carry_out, sum;

// creating the instance of the module we want to test
ex2 fa(a, b, carry_in, sum, carry_out);

initial
begin
	a = 1'b0;
	b = 1'b1;
	carry_in = 1'b0;
	#5; // pause (5 units of delay )
	carry_in = 1'b1;
	#5;
	a = 1'b1;
	b = 1'b0;
	#5;
	carry_in = 1'b0;
	#5
	a = 1'b0;
	b = 1'b0;
	#5
	carry_in = 1'b1;
	#5
	a = 1'b1;
	b = 1'b1;
	#5;
	carry_in = 1'b0;
end

// print signal values on every change
initial
$monitor("a= %b b = %b carry_in = %b sum = %b carry_out = %b", a, b, carry_in, sum, carry_out);

initial
$dumpvars;

endmodule

Lab10/ex2/simulation/modelsim/dump.vcd
$date
	Thu Nov 05 20:48:29 2020
$end
$version
	ModelSim Version 2020.1
$end
$timescale
	1ps
$end

$scope module testbench $end
$var reg 1 ! a $end
$var reg 1 " b $end
$var reg 1 # carry_in $end
$var wire 1 $ carry_out $end
$var wire 1 % sum $end

$scope module fa $end
$var wire 1 & i_bit1 $end
$var wire 1 ' i_bit2 $end
$var wire 1 ( cin $end
$var wire 1 $ sum $end
$var wire 1 % cout $end
$upscope $end
$upscope $end
$enddefinitions $end
#0
$dumpvars
0!
1"
0#
1$
0%
0(
1'
0&
$end
#5
1#
1(
0$
1%
#10
1!
0"
1&
0'
#15
0#
0(
1$
0%
#20
0!
0&
0$
#25
1#
1(
1$
#30
1!
1"
1&
1'
1%
#35
0#
0(
0$
