Lab13/alu_decoder.v
module alu_decoder(
	input [5:0] ALUOp,
	input [1:0] funct,
	output reg [2:0] ALUControl
);

always@ (*) begin
	case (ALUOp)
		2'b00: ALUControl	= 3'b010;
		2'b01: ALUControl = 3'b110;
		2'b10: begin
			case (funct)
				6'h20: begin
					ALUControl	= 3'b010;
				end
				6'h22: begin
					ALUControl	= 3'b110;
				end
				6'h24: begin
					ALUControl	= 3'b000;
				end
				6'h25: begin
					ALUControl	= 3'b001;
				end
				6'h2A: begin
					ALUControl	= 3'b111;
				end
			endcase
		end
	endcase
end


endmodule

Lab13/main_decoder.v
module main_decoder (
	input [5:0] opcode,
	output reg MemtoReg, MemWrite, Branch, ALUSrc, RegDst, RegWrite,
	output reg [1:0] ALUOp
);

always@ (*) begin
	case (opcode)
		6'h00: begin
			RegWrite = 1;
			RegDst = 1;
			ALUSrc = 0;
			Branch = 0;
			MemWrite = 0;
			MemtoReg = 0;
			ALUOp = 2'b10;
		end
		6'h23: begin
			RegWrite = 1;
			RegDst = 0;
			ALUSrc = 1;
			Branch = 0;
			MemWrite = 0;
			MemtoReg = 1;
			ALUOp = 2'b00;
		end
		6'h2B: begin
			RegWrite = 0;
			ALUSrc = 1;
			Branch = 0;
			MemWrite = 1;
			ALUOp = 2'b00;
		end
		6'h04	: begin
			RegWrite = 0;
			ALUSrc = 0;
			Branch = 1;
			MemWrite = 0;
			ALUOp = 2'b01;
		end
	endcase
end

endmodule

Lab13/decoder.v
module decoder(
	input [5:0] opcode, funct,
	output MemtoReg, MemWrite, Branch, ALUSrc, RegDst, RegWrite,
 	output [2:0] ALUControl
);

	wire [1:0] ALUOp;

	main_decoder hahahha(opcode, MemtoReg, MemWrite, Branch, ALUSrc, RedDst, RegWrite, ALUOp);
	alu_decoder ahahah(ALUOp, funct, ALUControl);

endmodule

Lab13/testbench.v
module testbench;

// input and output test signals
reg [5:0] opcode, funct;
wire MemtoReg, MemWrite, Branch, ALUSrc, RegDst, RegWrite;
wire [2:0] ALUControl;

decoder cu(opcode, funct, MemtoReg, MemWrite, Branch, ALUSrc, RegDst, RegWrite, ALUControl);

initial
begin
opcode = 6'h00;
funct = 6'h20;
#5;
funct = 6'h22;
#5;
funct = 6'h24;
#5;
funct = 6'h25;
#5;
funct = 6'h2A;
#5;
opcode = 6'h23;
#5;
opcode = 6'h2B;
#5;
opcode = 6'h04;
end

initial
$monitor("opcode = 0x%h RegWrite = %b RegDst = %b ALUSrc = %b Branch = %b MemWrite = %b MemtoReg = %b funct = 0x%h ALUControl = %b", opcode, RegWrite, RegDst, ALUSrc, Branch, MemWrite, MemtoReg, funct, ALUControl);

initial
$dumpvars;

endmodule

Lab13/simulation/modelsim/dump.vcd
$date
	Thu Nov 26 21:36:17 2020
$end
$version
	ModelSim Version 2020.1
$end
$timescale
	1ps
$end

$scope module testbench $end
$var reg 6 ! opcode [5:0] $end
$var reg 6 " funct [5:0] $end
$var wire 1 # MemtoReg $end
$var wire 1 $ MemWrite $end
$var wire 1 % Branch $end
$var wire 1 & ALUSrc $end
$var wire 1 ' RegDst $end
$var wire 1 ( RegWrite $end
$var wire 1 ) ALUControl [2] $end
$var wire 1 * ALUControl [1] $end
$var wire 1 + ALUControl [0] $end

$scope module cu $end
$var wire 1 , opcode [5] $end
$var wire 1 - opcode [4] $end
$var wire 1 . opcode [3] $end
$var wire 1 / opcode [2] $end
$var wire 1 0 opcode [1] $end
$var wire 1 1 opcode [0] $end
$var wire 1 2 funct [5] $end
$var wire 1 3 funct [4] $end
$var wire 1 4 funct [3] $end
$var wire 1 5 funct [2] $end
$var wire 1 6 funct [1] $end
$var wire 1 7 funct [0] $end
$var wire 1 # MemtoReg $end
$var wire 1 $ MemWrite $end
$var wire 1 % Branch $end
$var wire 1 & ALUSrc $end
$var wire 1 ' RegDst $end
$var wire 1 ( RegWrite $end
$var wire 1 ) ALUControl [2] $end
$var wire 1 * ALUControl [1] $end
$var wire 1 + ALUControl [0] $end
$var wire 1 8 ALUOp [1] $end
$var wire 1 9 ALUOp [0] $end
$var wire 1 : RedDst $end

$scope module hahahha $end
$var wire 1 , opcode [5] $end
$var wire 1 - opcode [4] $end
$var wire 1 . opcode [3] $end
$var wire 1 / opcode [2] $end
$var wire 1 0 opcode [1] $end
$var wire 1 1 opcode [0] $end
$var reg 1 ; MemtoReg $end
$var reg 1 < MemWrite $end
$var reg 1 = Branch $end
$var reg 1 > ALUSrc $end
$var reg 1 ? RegDst $end
$var reg 1 @ RegWrite $end
$var reg 2 A ALUOp [1:0] $end
$upscope $end

$scope module ahahah $end
$var wire 1 B ALUOp [5] $end
$var wire 1 C ALUOp [4] $end
$var wire 1 D ALUOp [3] $end
$var wire 1 E ALUOp [2] $end
$var wire 1 8 ALUOp [1] $end
$var wire 1 9 ALUOp [0] $end
$var wire 1 6 funct [1] $end
$var wire 1 7 funct [0] $end
$var reg 3 F ALUControl [2:0] $end
$upscope $end
$upscope $end
$upscope $end
$enddefinitions $end
#0
$dumpvars
b0 !
b100000 "
0;
0<
0=
0>
1?
1@
b10 A
bx F
0#
0$
0%
0&
z'
1(
x+
x*
x)
09
18
1:
07
06
05
04
03
12
01
00
0/
0.
0-
0,
zE
zD
zC
zB
$end
#5
b100010 "
16
#10
b100100 "
06
15
#15
b100101 "
17
#20
b101010 "
07
16
05
14
#25
b100011 !
11
10
1,
0?
1>
1;
b0 A
0:
1&
1#
08
#30
b101011 !
1.
0@
1<
0(
1$
#35
b100 !
01
00
1/
0.
0,
0>
1=
0<
b1 A
0&
1%
0$
19
